MANIFEST.in
setup.py
Flask_MustacheJS.egg-info/PKG-INFO
Flask_MustacheJS.egg-info/SOURCES.txt
Flask_MustacheJS.egg-info/dependency_links.txt
Flask_MustacheJS.egg-info/not-zip-safe
Flask_MustacheJS.egg-info/requires.txt
Flask_MustacheJS.egg-info/top_level.txt
flask_mustache/__init__.py
flask_mustache/static/mustache-loader.js
flask_mustache/templates/_template_script_block.jinja