Metadata-Version: 1.1
Name: Flask-MustacheJS
Version: 0.6.0
Summary: Mustache integration in Flask, with Jinja and client-side libraries.
Home-page: https://github.com/bradleywright/flask-mustachejs
Author: Bradley Wright
Author-email: brad@intranation.com
License: BSD
Platform: any
Classifier: Environment :: Web Environment
Classifier: Intended Audience :: Developers
Classifier: License :: OSI Approved :: BSD License
Classifier: Operating System :: OS Independent
Classifier: Programming Language :: Python
Classifier: Topic :: Internet :: WWW/HTTP :: Dynamic Content
Classifier: Topic :: Software Development :: Libraries :: Python Modules
